pyckster/__init__.py
pyckster/__main__.py
pyckster/auto_picking.py
pyckster/bayesian_inversion.py
pyckster/core.py
pyckster/dispersion_stack_viewer.py
pyckster/inversion_app.py
pyckster/inversion_manager.py
pyckster/inversion_visualizer.py
pyckster/ipython_console.py
pyckster/mpl_export.py
pyckster/obspy_utils.py
pyckster/pick_io.py
pyckster/pyqtgraph_utils.py
pyckster/surface_wave_analysis.py
pyckster/surface_wave_profiling.py
pyckster/sw_utils.py
pyckster/tab_factory.py
pyckster/visualization_utils.py
pyckster-26.1.6.dist-info/licenses/LICENCE
pyckster-26.1.6.dist-info/METADATA
pyckster-26.1.6.dist-info/WHEEL
pyckster-26.1.6.dist-info/entry_points.txt
pyckster-26.1.6.dist-info/top_level.txt
pyckster-26.1.6.dist-info/RECORD
