Metadata-Version: 2.4
Name: pyckster
Version: 26.1.6
Summary: A PyQt5-based GUI for the processing and analysis of active near-surface seismic data
Home-page: https://gitlab.in2p3.fr/metis-geophysics/pyckster
Author: Sylvain Pasquet
Author-email: sylvain.pasquet@sorbonne-universite.fr
License: GPLv3
Requires-Python: >=3.7, <4
License-File: LICENCE
Requires-Dist: PyQt5>=5.15.4
Requires-Dist: pyqtgraph
Requires-Dist: numpy
Requires-Dist: scipy
Requires-Dist: matplotlib
Requires-Dist: obspy
Requires-Dist: qtawesome
Provides-Extra: tt-inversion
Requires-Dist: pygimli; extra == "tt-inversion"
Dynamic: author
Dynamic: author-email
Dynamic: description
Dynamic: description-content-type
Dynamic: home-page
Dynamic: license
Dynamic: license-file
Dynamic: provides-extra
Dynamic: requires-dist
Dynamic: requires-python
Dynamic: summary
